<?xml version="1.0" encoding="UTF-8"?>
<!DOCTYPE users SYSTEM "usersDTD.dtd">
<users
       xmlns:xsi="http://www.w3.org/2001/XMLSchema-instance"
       xsi:noNamespaceSchemaLocation="users.xsd">

  <user id="u10">
    <name>Aymane</name>
    <role typeRole="devops"/> <!--devops | cloud-->
    <job typeJob="chef_projet"/> <!--technicien | ingenieur |  chef_projet | manager -->
  </user>

  <user id="u11">
    <name>Otman</name>
    <role typeRole="cloud"/>
    <job typeJob="ingenieur"/>
  </user>

  <user id="u12">
    <name>Houssam</name>
    <role typeRole="devops"/>
    <job typeJob="manager"/>
  </user>

</users>
